central_das_emendas_teste/__init__.py
central_das_emendas_teste/data_loader.py
central_das_emendas_teste-0.1.0.dist-info/METADATA
central_das_emendas_teste-0.1.0.dist-info/WHEEL
central_das_emendas_teste-0.1.0.dist-info/top_level.txt
central_das_emendas_teste-0.1.0.dist-info/RECORD
