Metadata-Version: 2.4
Name: central_das_emendas_teste
Version: 0.1.0
Summary: Baixa e carrega em DataFrame o CSV de emendas do Google Drive
Author-email: Caio Sousa <c.sousa@poli.ufrj.br>
License-Expression: MIT
Project-URL: Homepage, https://github.com/caiosousareis
Requires-Python: >=3.9
Requires-Dist: pandas>=2.0
Requires-Dist: gdown>=5.0
